raven/__init__.py
raven/clients.py
raven/exceptions.py
raven/py.typed
raven/http/client.py
raven/models/captcha.py
raven/models/response.py
raven/providers/cloudflare.py
raven/providers/google.py
raven/services/captcha_service.py
raven_python_client-1.0.1.dist-info/licenses/LICENSE
raven_python_client-1.0.1.dist-info/METADATA
raven_python_client-1.0.1.dist-info/WHEEL
raven_python_client-1.0.1.dist-info/top_level.txt
raven_python_client-1.0.1.dist-info/RECORD
